ndx_speech/__init__.py
ndx_speech/spec/ndx-speech.extensions.yaml
ndx_speech/spec/ndx-speech.namespace.yaml
ndx_speech/spec/speech.extensions.yaml
ndx_speech/spec/speech.namespace.yaml
ndx_speech/test/__init__.py
ndx_speech/test/test.py
ndx_speech-0.1.4.dist-info/LICENSE.txt
ndx_speech-0.1.4.dist-info/METADATA
ndx_speech-0.1.4.dist-info/WHEEL
ndx_speech-0.1.4.dist-info/top_level.txt
ndx_speech-0.1.4.dist-info/RECORD
